Metadata-Version: 2.1
Name: opcodify
Version: 0.1.3
Summary: opcodify is a command-line tool designed to simplify the process of visualizing Opcodes within Solidity Smart Contracts. With opcodify, you can effortlessly generate treemap visualizations that provide insights into the distribution of opcodes used within your contracts.
Author: Sumit Banik
Author-email: sumitbanik02@gmail.com
License: Apache License 2.0
License-File: LICENSE.md
